LICENSE
MANIFEST.in
README.txt
setup.py
GeoCal/Geo.py
GeoCal/LICENSE
GeoCal/RollLabel.py
GeoCal/Task.py
GeoCal/UI.py
GeoCal/__init__.py
GeoCal/form.ui
GeoCal/images.py
GeoCal/QSS/task_ui.qss
GeoCal/__pycache__/Geo.cpython-35.pyc
GeoCal/__pycache__/RollLabel.cpython-35.pyc
GeoCal/__pycache__/Task.cpython-35.pyc
GeoCal/__pycache__/UI.cpython-35.pyc
GeoCal/__pycache__/__init__.cpython-35.pyc
GeoCal/__pycache__/images.cpython-35.pyc
geo_com_cal.egg-info/PKG-INFO
geo_com_cal.egg-info/SOURCES.txt
geo_com_cal.egg-info/dependency_links.txt
geo_com_cal.egg-info/requires.txt
geo_com_cal.egg-info/top_level.txt