Metadata-Version: 1.2
Name: geo-com-cal
Version: 0.0.1
Summary: 基于python3.5+pyside2-5.15.1实现的大地测量综合计算，修正了样式表
Home-page: https://github.com
Author: pby
Author-email: 2567469480@qq.com
License: LGPL
Platform: any
Requires-Python: >=2.7
